odoo/addons/edi_edifact_oca/README.rst
odoo/addons/edi_edifact_oca/__init__.py
odoo/addons/edi_edifact_oca/__manifest__.py
odoo/addons/edi_edifact_oca/components/__init__.py
odoo/addons/edi_edifact_oca/components/party_data.py
odoo/addons/edi_edifact_oca/data/edi_backend_type.xml
odoo/addons/edi_edifact_oca/demo/edi_backend_demo.xml
odoo/addons/edi_edifact_oca/i18n/edi_edifact_oca.pot
odoo/addons/edi_edifact_oca/i18n/it.po
odoo/addons/edi_edifact_oca/readme/CONTRIBUTORS.rst
odoo/addons/edi_edifact_oca/readme/DESCRIPTION.rst
odoo/addons/edi_edifact_oca/static/description/icon.png
odoo/addons/edi_edifact_oca/static/description/index.html
odoo/addons/edi_edifact_oca/tests/__init__.py
odoo/addons/edi_edifact_oca/tests/test_party_data.py
odoo_addon_edi_edifact_oca-16.0.1.0.0.2.dist-info/METADATA
odoo_addon_edi_edifact_oca-16.0.1.0.0.2.dist-info/WHEEL
odoo_addon_edi_edifact_oca-16.0.1.0.0.2.dist-info/top_level.txt
odoo_addon_edi_edifact_oca-16.0.1.0.0.2.dist-info/RECORD
