Metadata-Version: 2.1
Name: odoo-addon-edi-edifact-oca
Version: 16.0.1.0.0.2
Summary: Define EDI backend type for EDIFACT.
Home-page: https://github.com/OCA/edi-framework
Author: Camptocamp,Odoo Community Association (OCA)
Author-email: support@odoo-community.org
License: AGPL-3
Platform: UNKNOWN
Classifier: Programming Language :: Python
Classifier: Framework :: Odoo
Classifier: Framework :: Odoo :: 16.0
Classifier: License :: OSI Approved :: GNU Affero General Public License v3
Classifier: Development Status :: 3 - Alpha
Requires-Python: >=3.10
Requires-Dist: odoo-addon-base-edifact <16.1dev,>=16.0dev
Requires-Dist: odoo-addon-edi-oca <16.1dev,>=16.0dev
Requires-Dist: odoo-addon-edi-party-data-oca <16.1dev,>=16.0dev
Requires-Dist: odoo <16.1dev,>=16.0a
